{"build_type": "release", "env_name": "pro16MHzatmega328", "libsource_dirs": ["c:\\Users\\tom_b\\LboroSpcTlm\\Project\\lib", "c:\\Users\\tom_b\\LboroSpcTlm\\Project\\.pio\\libdeps\\pro16MHzatmega328", "C:\\Users\\tom_b\\.platformio\\lib", "C:\\Users\\tom_b\\.platformio\\packages\\framework-arduino-avr\\libraries"], "defines": ["PLATFORMIO=60105", "ARDUINO_AVR_PRO", "F_CPU=16000000L", "ARDUINO_ARCH_AVR", "ARDUINO=10808", "__AVR_ATmega328P__"], "includes": {"build": ["c:\\Users\\tom_b\\LboroSpcTlm\\Project\\include", "c:\\Users\\tom_b\\LboroSpcTlm\\Project\\src", "c:\\Users\\tom_b\\LboroSpcTlm\\Project\\include", "c:\\Users\\tom_b\\LboroSpcTlm\\Project\\src", "C:\\Users\\tom_b\\.platformio\\packages\\framework-arduino-avr\\cores\\arduino", "C:\\Users\\tom_b\\.platformio\\packages\\framework-arduino-avr\\variants\\eightanaloginputs"], "compatlib": ["C:\\Users\\tom_b\\.platformio\\packages\\framework-arduino-avr\\libraries\\EEPROM\\src", "C:\\Users\\tom_b\\.platformio\\packages\\framework-arduino-avr\\libraries\\HID\\src", "C:\\Users\\tom_b\\.platformio\\packages\\framework-arduino-avr\\libraries\\SPI\\src", "C:\\Users\\tom_b\\.platformio\\packages\\framework-arduino-avr\\libraries\\SoftwareSerial\\src", "C:\\Users\\tom_b\\.platformio\\packages\\framework-arduino-avr\\libraries\\Wire\\src"], "toolchain": ["C:\\Users\\tom_b\\.platformio\\packages\\toolchain-atmelavr\\lib\\gcc\\avr\\5.4.0\\include", "C:\\Users\\tom_b\\.platformio\\packages\\toolchain-atmelavr\\lib\\gcc\\avr\\5.4.0\\include-fixed", "C:\\Users\\tom_b\\.platformio\\packages\\toolchain-atmelavr\\avr\\include"]}, "cc_flags": "-std=gnu11 -fno-fat-lto-objects -Os -Wall -ffunction-sections -fdata-sections -flto -mmcu=atmega328p", "cxx_flags": "-fno-exceptions -fno-threadsafe-statics -fpermissive -std=gnu++11 -Os -Wall -ffunction-sections -fdata-sections -flto -mmcu=atmega328p", "cc_path": "C:\\Users\\tom_b\\.platformio\\packages\\toolchain-atmelavr\\bin\\avr-gcc.exe", "cxx_path": "C:\\Users\\tom_b\\.platformio\\packages\\toolchain-atmelavr\\bin\\avr-g++.exe", "gdb_path": "C:\\Users\\tom_b\\.platformio\\packages\\toolchain-atmelavr\\bin\\avr-gdb.exe", "prog_path": "c:\\Users\\tom_b\\LboroSpcTlm\\Project\\.pio\\build\\pro16MHzatmega328\\firmware.elf", "svd_path": null, "compiler_type": "gcc", "targets": [{"name": "size", "title": "Program Size", "description": "Calculate program size", "group": "Platform"}, {"name": "upload", "title": "Upload", "description": null, "group": "Platform"}, {"name": "uploadeep", "title": "Upload EEPROM", "description": null, "group": "Platform"}, {"name": "program", "title": "Upload using Programmer", "description": null, "group": "Platform"}, {"name": "fuses", "title": "Set Fuses", "description": null, "group": "Platform"}, {"name": "bootloader", "title": "Burn Bootloader", "description": null, "group": "Platform"}], "extra": {"flash_images": []}}